<NUDMATERIAL polycount="1">
  <mesh name="bahamut_dangerzone_C_O_OBJ_O_HIR">
    <polygon id="0">
      <material flags="a2000000" srcFactor="0" dstFactor="0" AlphaFunc="0" AlphaTest="0" RefAlpha="0" cullmode="405" zbuffoff="0">
        <texture hash="2000010b" wrapmodeS="3" wrapmodeT="3" minfilter="3" magfilter="2" mipdetail="2" />
        <param name="NU_diffuseColor">1 1 1 1 </param>
        <param name="NU_materialHash">bfe937eb 0 0 0 </param>
      </material>
    </polygon>
  </mesh>
</NUDMATERIAL>