<NUDMATERIAL polycount="7">
  <mesh name="Mii">
    <polygon id="0">
      <material flags="a4001001" srcFactor="1" dstFactor="1" AlphaFunc="0" AlphaTest="0" RefAlpha="0" cullmode="405" zbuffoff="0">
        <texture hash="20000163" wrapmodeS="3" wrapmodeT="3" minfilter="3" magfilter="2" mipdetail="6" />
        <param name="NU_colorSamplerUV">1 1 0 0 </param>
        <param name="NU_diffuseColor">1 1 1 1 </param>
        <param name="NU_materialHash">d86839b1 0 0 0 </param>
      </material>
    </polygon>
    <polygon id="1">
      <material flags="a4001001" srcFactor="0" dstFactor="0" AlphaFunc="0" AlphaTest="0" RefAlpha="0" cullmode="405" zbuffoff="0">
        <texture hash="2000015e" wrapmodeS="1" wrapmodeT="1" minfilter="3" magfilter="2" mipdetail="6" />
        <param name="NU_colorSamplerUV">1 1 0 0 </param>
        <param name="NU_diffuseColor">1 1 1 1 </param>
        <param name="NU_materialHash">de536b38 0 0 0 </param>
      </material>
    </polygon>
    <polygon id="2">
      <material flags="a4001001" srcFactor="0" dstFactor="0" AlphaFunc="0" AlphaTest="0" RefAlpha="0" cullmode="405" zbuffoff="0">
        <texture hash="2000015f" wrapmodeS="3" wrapmodeT="3" minfilter="3" magfilter="2" mipdetail="6" />
        <param name="NU_colorSamplerUV">1 1 0 0 </param>
        <param name="NU_diffuseColor">1 1 1 1 </param>
        <param name="NU_materialHash">2b42688d 0 0 0 </param>
      </material>
    </polygon>
    <polygon id="3">
      <material flags="a4001001" srcFactor="0" dstFactor="0" AlphaFunc="0" AlphaTest="0" RefAlpha="0" cullmode="405" zbuffoff="0">
        <texture hash="20000160" wrapmodeS="1" wrapmodeT="1" minfilter="3" magfilter="2" mipdetail="6" />
        <param name="NU_colorSamplerUV">1 1 0 0 </param>
        <param name="NU_diffuseColor">1 1 1 1 </param>
        <param name="NU_materialHash">c5a17250 0 0 0 </param>
      </material>
    </polygon>
    <polygon id="4">
      <material flags="a4001001" srcFactor="1" dstFactor="1" AlphaFunc="0" AlphaTest="0" RefAlpha="0" cullmode="405" zbuffoff="0">
        <texture hash="20000161" wrapmodeS="3" wrapmodeT="3" minfilter="3" magfilter="2" mipdetail="6" />
        <param name="NU_colorSamplerUV">1 1 0 0 </param>
        <param name="NU_diffuseColor">1 1 1 1 </param>
        <param name="NU_materialHash">2f5612 0 0 0 </param>
      </material>
    </polygon>
    <polygon id="5">
      <material flags="a4001001" srcFactor="1" dstFactor="1" AlphaFunc="0" AlphaTest="0" RefAlpha="0" cullmode="0" zbuffoff="0">
        <texture hash="20000162" wrapmodeS="3" wrapmodeT="1" minfilter="3" magfilter="2" mipdetail="6" />
        <param name="NU_colorSamplerUV">1 1 0 0 </param>
        <param name="NU_diffuseColor">1 1 1 1 </param>
        <param name="NU_materialHash">c546690b 0 0 0 </param>
      </material>
    </polygon>
    <polygon id="6">
      <material flags="a4001001" srcFactor="0" dstFactor="0" AlphaFunc="0" AlphaTest="0" RefAlpha="0" cullmode="405" zbuffoff="0">
        <texture hash="2000031d" wrapmodeS="2" wrapmodeT="1" minfilter="3" magfilter="2" mipdetail="6" />
        <param name="NU_colorSamplerUV">1 1 0 0 </param>
        <param name="NU_diffuseColor">1 1 1 1 </param>
        <param name="NU_materialHash">30b071e5 0 0 0 </param>
      </material>
    </polygon>
  </mesh>
</NUDMATERIAL>