<NUDMATERIAL polycount="12">
  <mesh name="Body01M_VIS_O_OBJ">
    <polygon id="0">
      <material flags="92001001" srcFactor="5" dstFactor="1" AlphaFunc="0" AlphaTest="0" RefAlpha="0" cullmode="405" zbuffoff="0">
        <texture hash="40075202" wrapmodeS="3" wrapmodeT="3" minfilter="3" magfilter="2" mipdetail="6" />
        <param name="NU_colorSamplerUV">1 1 0 0 </param>
        <param name="NU_blinkColor">0 0 0 0 </param>
        <param name="NU_alphaBlendParams">0 0 0 0 </param>
        <param name="NU_materialHash">1677b618 0 0 0 </param>
      </material>
    </polygon>
    <polygon id="1">
      <material flags="92001001" srcFactor="1" dstFactor="1" AlphaFunc="0" AlphaTest="0" RefAlpha="0" cullmode="405" zbuffoff="0">
        <texture hash="40075201" wrapmodeS="3" wrapmodeT="3" minfilter="3" magfilter="2" mipdetail="6" />
        <param name="NU_colorSamplerUV">1 1 0 0 </param>
        <param name="NU_blinkColor">0 0 0 0 </param>
        <param name="NU_alphaBlendParams">0 0 0 0 </param>
        <param name="NU_materialHash">9027cc28 0 0 0 </param>
      </material>
    </polygon>
    <polygon id="2">
      <material flags="92001001" srcFactor="1" dstFactor="1" AlphaFunc="0" AlphaTest="0" RefAlpha="0" cullmode="405" zbuffoff="0">
        <texture hash="40075200" wrapmodeS="3" wrapmodeT="3" minfilter="3" magfilter="2" mipdetail="6" />
        <param name="NU_colorSamplerUV">1 1 0 0 </param>
        <param name="NU_blinkColor">0 0 0 0 </param>
        <param name="NU_alphaBlendParams">0 0 0 0 </param>
        <param name="NU_materialHash">3692f276 0 0 0 </param>
      </material>
    </polygon>
  </mesh>
  <mesh name="Body02M_VIS_O_OBJ">
    <polygon id="3">
      <material flags="92001001" srcFactor="5" dstFactor="1" AlphaFunc="0" AlphaTest="0" RefAlpha="0" cullmode="405" zbuffoff="0">
        <texture hash="40075202" wrapmodeS="3" wrapmodeT="3" minfilter="3" magfilter="2" mipdetail="6" />
        <param name="NU_colorSamplerUV">1 1 0 0 </param>
        <param name="NU_blinkColor">0 0 0 0 </param>
        <param name="NU_alphaBlendParams">0 0 0 0 </param>
        <param name="NU_materialHash">1677b618 0 0 0 </param>
      </material>
    </polygon>
    <polygon id="4">
      <material flags="92001001" srcFactor="1" dstFactor="1" AlphaFunc="0" AlphaTest="0" RefAlpha="0" cullmode="405" zbuffoff="0">
        <texture hash="40075201" wrapmodeS="3" wrapmodeT="3" minfilter="3" magfilter="2" mipdetail="6" />
        <param name="NU_colorSamplerUV">1 1 0 0 </param>
        <param name="NU_blinkColor">0 0 0 0 </param>
        <param name="NU_alphaBlendParams">0 0 0 0 </param>
        <param name="NU_materialHash">9027cc28 0 0 0 </param>
      </material>
    </polygon>
    <polygon id="5">
      <material flags="92001001" srcFactor="1" dstFactor="1" AlphaFunc="0" AlphaTest="0" RefAlpha="0" cullmode="405" zbuffoff="0">
        <texture hash="40075200" wrapmodeS="3" wrapmodeT="3" minfilter="3" magfilter="2" mipdetail="6" />
        <param name="NU_colorSamplerUV">1 1 0 0 </param>
        <param name="NU_blinkColor">0 0 0 0 </param>
        <param name="NU_alphaBlendParams">0 0 0 0 </param>
        <param name="NU_materialHash">3692f276 0 0 0 </param>
      </material>
    </polygon>
  </mesh>
  <mesh name="Body03M_VIS_O_OBJ">
    <polygon id="6">
      <material flags="92001001" srcFactor="5" dstFactor="1" AlphaFunc="0" AlphaTest="0" RefAlpha="0" cullmode="405" zbuffoff="0">
        <texture hash="40075202" wrapmodeS="3" wrapmodeT="3" minfilter="3" magfilter="2" mipdetail="6" />
        <param name="NU_colorSamplerUV">1 1 0 0 </param>
        <param name="NU_blinkColor">0 0 0 0 </param>
        <param name="NU_alphaBlendParams">0 0 0 0 </param>
        <param name="NU_materialHash">1677b618 0 0 0 </param>
      </material>
    </polygon>
    <polygon id="7">
      <material flags="92001001" srcFactor="1" dstFactor="1" AlphaFunc="0" AlphaTest="0" RefAlpha="0" cullmode="405" zbuffoff="0">
        <texture hash="40075201" wrapmodeS="3" wrapmodeT="3" minfilter="3" magfilter="2" mipdetail="6" />
        <param name="NU_colorSamplerUV">1 1 0 0 </param>
        <param name="NU_blinkColor">0 0 0 0 </param>
        <param name="NU_alphaBlendParams">0 0 0 0 </param>
        <param name="NU_materialHash">9027cc28 0 0 0 </param>
      </material>
    </polygon>
    <polygon id="8">
      <material flags="92001001" srcFactor="1" dstFactor="1" AlphaFunc="0" AlphaTest="0" RefAlpha="0" cullmode="405" zbuffoff="0">
        <texture hash="40075200" wrapmodeS="3" wrapmodeT="3" minfilter="3" magfilter="2" mipdetail="6" />
        <param name="NU_colorSamplerUV">1 1 0 0 </param>
        <param name="NU_blinkColor">0 0 0 0 </param>
        <param name="NU_alphaBlendParams">0 0 0 0 </param>
        <param name="NU_materialHash">3692f276 0 0 0 </param>
      </material>
    </polygon>
  </mesh>
  <mesh name="Body04M_VIS_O_OBJ">
    <polygon id="9">
      <material flags="92001001" srcFactor="5" dstFactor="1" AlphaFunc="0" AlphaTest="0" RefAlpha="0" cullmode="405" zbuffoff="0">
        <texture hash="40075202" wrapmodeS="3" wrapmodeT="3" minfilter="3" magfilter="2" mipdetail="6" />
        <param name="NU_colorSamplerUV">1 1 0 0 </param>
        <param name="NU_blinkColor">0 0 0 0 </param>
        <param name="NU_alphaBlendParams">0 0 0 0 </param>
        <param name="NU_materialHash">1677b618 0 0 0 </param>
      </material>
    </polygon>
    <polygon id="10">
      <material flags="92001001" srcFactor="1" dstFactor="1" AlphaFunc="0" AlphaTest="0" RefAlpha="0" cullmode="405" zbuffoff="0">
        <texture hash="40075201" wrapmodeS="3" wrapmodeT="3" minfilter="3" magfilter="2" mipdetail="6" />
        <param name="NU_colorSamplerUV">1 1 0 0 </param>
        <param name="NU_blinkColor">0 0 0 0 </param>
        <param name="NU_alphaBlendParams">0 0 0 0 </param>
        <param name="NU_materialHash">9027cc28 0 0 0 </param>
      </material>
    </polygon>
    <polygon id="11">
      <material flags="92001001" srcFactor="1" dstFactor="1" AlphaFunc="0" AlphaTest="0" RefAlpha="0" cullmode="405" zbuffoff="0">
        <texture hash="40075200" wrapmodeS="3" wrapmodeT="3" minfilter="3" magfilter="2" mipdetail="6" />
        <param name="NU_colorSamplerUV">1 1 0 0 </param>
        <param name="NU_blinkColor">0 0 0 0 </param>
        <param name="NU_alphaBlendParams">0 0 0 0 </param>
        <param name="NU_materialHash">3692f276 0 0 0 </param>
      </material>
    </polygon>
  </mesh>
</NUDMATERIAL>