<NUDMATERIAL polycount="12">
  <mesh name="group152_O_OBJ_O_HIR">
    <polygon id="0">
      <material flags="a2131045" srcFactor="0" dstFactor="0" AlphaFunc="0" AlphaTest="0" RefAlpha="0" cullmode="405" zbuffoff="0">
        <texture hash="20000183" wrapmodeS="3" wrapmodeT="3" minfilter="3" magfilter="2" mipdetail="6" />
        <texture hash="2000016c" wrapmodeS="3" wrapmodeT="3" minfilter="3" magfilter="2" mipdetail="6" />
        <param name="NU_colorSamplerUV">1 1 0 0 </param>
        <param name="NU_reflectionParams">2 0 0 0 </param>
        <param name="NU_fogParams">0 2300 0.1 0.8 </param>
        <param name="NU_fresnelColor">0.442 0.691 0.558 0 </param>
        <param name="NU_fresnelParams">8 0 0 0 </param>
        <param name="NU_fogColor">1 1 1 0 </param>
        <param name="NU_diffuseColor">1.5 1.5 1.5 1 </param>
        <param name="NU_materialHash">57325c9 0 0 0 </param>
      </material>
    </polygon>
    <polygon id="1">
      <material flags="a2111045" srcFactor="0" dstFactor="0" AlphaFunc="0" AlphaTest="0" RefAlpha="0" cullmode="405" zbuffoff="0">
        <texture hash="2000016a" wrapmodeS="1" wrapmodeT="1" minfilter="3" magfilter="2" mipdetail="6" />
        <texture hash="2000016c" wrapmodeS="3" wrapmodeT="3" minfilter="3" magfilter="2" mipdetail="6" />
        <param name="NU_colorSamplerUV">1 1 0 0 </param>
        <param name="NU_reflectionParams">1 0 0 0 </param>
        <param name="NU_fogParams">0 2300 0.1 0.8 </param>
        <param name="NU_fogColor">1 1 1 0 </param>
        <param name="NU_diffuseColor">1.8 1.8 1.8 1 </param>
        <param name="NU_materialHash">9357cd81 0 0 0 </param>
      </material>
    </polygon>
    <polygon id="2">
      <material flags="a2011041" srcFactor="0" dstFactor="0" AlphaFunc="0" AlphaTest="0" RefAlpha="0" cullmode="405" zbuffoff="0">
        <texture hash="200000ef" wrapmodeS="1" wrapmodeT="1" minfilter="3" magfilter="2" mipdetail="6" />
        <param name="NU_colorSamplerUV">1 1 0 0 </param>
        <param name="NU_fogParams">0 2300 0.1 0.8 </param>
        <param name="NU_fogColor">1 1 1 0 </param>
        <param name="NU_diffuseColor">1.5 1.5 1.5 1 </param>
        <param name="NU_materialHash">a4e0d77e 0 0 0 </param>
      </material>
    </polygon>
    <polygon id="3">
      <material flags="a2131045" srcFactor="0" dstFactor="0" AlphaFunc="0" AlphaTest="0" RefAlpha="0" cullmode="405" zbuffoff="0">
        <texture hash="20000129" wrapmodeS="1" wrapmodeT="1" minfilter="3" magfilter="2" mipdetail="6" />
        <texture hash="2000016c" wrapmodeS="3" wrapmodeT="3" minfilter="3" magfilter="2" mipdetail="6" />
        <param name="NU_colorSamplerUV">1 1 0 0 </param>
        <param name="NU_reflectionParams">2 0 0 0 </param>
        <param name="NU_fogParams">0 2300 0.1 0.8 </param>
        <param name="NU_fresnelColor">0.904 0.671 0.365 0.2 </param>
        <param name="NU_fresnelParams">3 0 0 0 </param>
        <param name="NU_fogColor">1 1 1 0 </param>
        <param name="NU_diffuseColor">1 1 1 1 </param>
        <param name="NU_materialHash">18465dd9 0 0 0 </param>
      </material>
    </polygon>
    <polygon id="4">
      <material flags="a2131045" srcFactor="0" dstFactor="0" AlphaFunc="0" AlphaTest="0" RefAlpha="0" cullmode="405" zbuffoff="0">
        <texture hash="2000017e" wrapmodeS="1" wrapmodeT="1" minfilter="3" magfilter="2" mipdetail="6" />
        <texture hash="2000016c" wrapmodeS="3" wrapmodeT="3" minfilter="3" magfilter="2" mipdetail="6" />
        <param name="NU_colorSamplerUV">1 1 0 0 </param>
        <param name="NU_reflectionParams">2 0 0 0 </param>
        <param name="NU_fogParams">0 2300 0.1 0.8 </param>
        <param name="NU_fresnelColor">0.904 0.671 0.365 0.2 </param>
        <param name="NU_fresnelParams">3 0 0 0 </param>
        <param name="NU_fogColor">1 1 1 0 </param>
        <param name="NU_diffuseColor">1 1 1 1 </param>
        <param name="NU_materialHash">7c9c212f 0 0 0 </param>
      </material>
    </polygon>
    <polygon id="5">
      <material flags="a2131045" srcFactor="0" dstFactor="0" AlphaFunc="0" AlphaTest="0" RefAlpha="0" cullmode="405" zbuffoff="0">
        <texture hash="2000012f" wrapmodeS="3" wrapmodeT="3" minfilter="3" magfilter="2" mipdetail="6" />
        <texture hash="2000016c" wrapmodeS="3" wrapmodeT="3" minfilter="3" magfilter="2" mipdetail="6" />
        <param name="NU_colorSamplerUV">1 1 0 0 </param>
        <param name="NU_reflectionParams">3 0 0 0 </param>
        <param name="NU_fogParams">0 2300 0.1 0.8 </param>
        <param name="NU_fresnelColor">0.854 0.798 0.547 0 </param>
        <param name="NU_fresnelParams">8 0 0 0 </param>
        <param name="NU_fogColor">1 1 1 0 </param>
        <param name="NU_diffuseColor">1.5 1.5 1.5 1 </param>
        <param name="NU_materialHash">235b75f1 0 0 0 </param>
      </material>
    </polygon>
    <polygon id="6">
      <material flags="a2131045" srcFactor="0" dstFactor="0" AlphaFunc="0" AlphaTest="0" RefAlpha="0" cullmode="405" zbuffoff="0">
        <texture hash="20000109" wrapmodeS="1" wrapmodeT="1" minfilter="3" magfilter="2" mipdetail="6" />
        <texture hash="2000016c" wrapmodeS="3" wrapmodeT="3" minfilter="3" magfilter="2" mipdetail="6" />
        <param name="NU_colorSamplerUV">1 1 0 0 </param>
        <param name="NU_reflectionParams">1 0 0 0 </param>
        <param name="NU_fogParams">0 2300 0.1 0.8 </param>
        <param name="NU_fresnelColor">1 0.942 0.303 0 </param>
        <param name="NU_fresnelParams">0.3 0 0 0 </param>
        <param name="NU_fogColor">1 1 1 0 </param>
        <param name="NU_diffuseColor">2 1.98 1.6 1 </param>
        <param name="NU_materialHash">d72515d0 0 0 0 </param>
      </material>
    </polygon>
    <polygon id="7">
      <material flags="a2011041" srcFactor="0" dstFactor="0" AlphaFunc="0" AlphaTest="0" RefAlpha="0" cullmode="405" zbuffoff="0">
        <texture hash="20000109" wrapmodeS="3" wrapmodeT="3" minfilter="3" magfilter="2" mipdetail="6" />
        <param name="NU_colorSamplerUV">1 1 0 0 </param>
        <param name="NU_fogParams">0 2300 0.1 0.8 </param>
        <param name="NU_fogColor">1 1 1 0 </param>
        <param name="NU_diffuseColor">1.5 1.47555 1.011 1 </param>
        <param name="NU_materialHash">654ec84f 0 0 0 </param>
      </material>
    </polygon>
    <polygon id="8">
      <material flags="a2011001" srcFactor="0" dstFactor="0" AlphaFunc="0" AlphaTest="0" RefAlpha="0" cullmode="405" zbuffoff="0">
        <texture hash="200000f2" wrapmodeS="1" wrapmodeT="1" minfilter="3" magfilter="2" mipdetail="6" />
        <param name="NU_colorSamplerUV">1 1 0 0 </param>
        <param name="NU_fogParams">0 2300 0.1 0.8 </param>
        <param name="NU_fogColor">1 1 1 0 </param>
        <param name="NU_diffuseColor">1 1 1 1 </param>
        <param name="NU_materialHash">88ffa583 0 0 0 </param>
      </material>
    </polygon>
    <polygon id="9">
      <material flags="a2131045" srcFactor="0" dstFactor="0" AlphaFunc="0" AlphaTest="0" RefAlpha="0" cullmode="405" zbuffoff="0">
        <texture hash="20000169" wrapmodeS="1" wrapmodeT="1" minfilter="3" magfilter="2" mipdetail="6" />
        <texture hash="2000016c" wrapmodeS="3" wrapmodeT="3" minfilter="3" magfilter="2" mipdetail="6" />
        <param name="NU_colorSamplerUV">1 1 0 0 </param>
        <param name="NU_reflectionParams">0.7 0 0 0 </param>
        <param name="NU_fogParams">0 2300 0.1 0.8 </param>
        <param name="NU_fresnelColor">1 1 0.483 0 </param>
        <param name="NU_fresnelParams">1 0 0 0 </param>
        <param name="NU_fogColor">1 1 1 0 </param>
        <param name="NU_diffuseColor">1.8 1.70046 1.5156 1 </param>
        <param name="NU_materialHash">d0cdd4a0 0 0 0 </param>
      </material>
    </polygon>
    <polygon id="10">
      <material flags="a2131045" srcFactor="0" dstFactor="0" AlphaFunc="0" AlphaTest="0" RefAlpha="0" cullmode="405" zbuffoff="0">
        <texture hash="2000017f" wrapmodeS="3" wrapmodeT="3" minfilter="3" magfilter="2" mipdetail="6" />
        <texture hash="2000016c" wrapmodeS="3" wrapmodeT="3" minfilter="3" magfilter="2" mipdetail="6" />
        <param name="NU_colorSamplerUV">1 1 0 0 </param>
        <param name="NU_reflectionParams">0.7 0 0 0 </param>
        <param name="NU_fogParams">0 2300 0.1 0.8 </param>
        <param name="NU_fresnelColor">0.258 0.308 0.528 0.27 </param>
        <param name="NU_fresnelParams">3 0 0 0 </param>
        <param name="NU_fogColor">1 1 1 0 </param>
        <param name="NU_diffuseColor">2 2 2 1 </param>
        <param name="NU_materialHash">4ad386 0 0 0 </param>
      </material>
    </polygon>
    <polygon id="11">
      <material flags="a2131045" srcFactor="0" dstFactor="0" AlphaFunc="0" AlphaTest="0" RefAlpha="0" cullmode="405" zbuffoff="0">
        <texture hash="20000181" wrapmodeS="1" wrapmodeT="3" minfilter="3" magfilter="2" mipdetail="6" />
        <texture hash="2000016c" wrapmodeS="3" wrapmodeT="3" minfilter="3" magfilter="2" mipdetail="6" />
        <param name="NU_colorSamplerUV">1 1 0 0 </param>
        <param name="NU_reflectionParams">0.7 0 0 0 </param>
        <param name="NU_fogParams">0 2300 0.1 0.8 </param>
        <param name="NU_fresnelColor">0.258 0.308 0.528 0 </param>
        <param name="NU_fresnelParams">1 0 0 0 </param>
        <param name="NU_fogColor">1 1 1 0 </param>
        <param name="NU_diffuseColor">2 2 2 1 </param>
        <param name="NU_materialHash">90e07657 0 0 0 </param>
      </material>
    </polygon>
  </mesh>
</NUDMATERIAL>