<NUDMATERIAL polycount="1">
  <mesh name="S00_clouds1_O_OBJ_O_SORTBIAS1000_">
    <polygon id="0">
      <material flags="a2003303" srcFactor="5" dstFactor="1" AlphaFunc="0" AlphaTest="0" RefAlpha="0" cullmode="405" zbuffoff="0">
        <texture hash="200000c5" wrapmodeS="1" wrapmodeT="1" minfilter="3" magfilter="2" mipdetail="6" />
        <texture hash="20000005" wrapmodeS="1" wrapmodeT="1" minfilter="3" magfilter="2" mipdetail="6" />
        <param name="NU_colorSamplerUV">1 1 0 0 </param>
        <param name="NU_normalSamplerAUV">1 1 1 0 </param>
        <param name="NU_diffuseColor">1.1 1.1 1.1 0 </param>
        <param name="NU_normalParams">1 0 0.02 0 </param>
        <param name="NU_materialHash">6e8a939f 0 0 0 </param>
      </material>
    </polygon>
  </mesh>
</NUDMATERIAL>