<NUDMATERIAL polycount="2">
  <mesh name="rcs">
    <polygon id="0">
      <material flags="a4010041" srcFactor="0" dstFactor="0" AlphaFunc="0" AlphaTest="0" RefAlpha="0" cullmode="405" zbuffoff="0">
        <texture hash="20000227" wrapmodeS="2" wrapmodeT="2" minfilter="2" magfilter="2" mipdetail="6" />
        <param name="NU_colorSamplerUV">1 1 0 0 </param>
        <param name="NU_fogParams">40 1200 0 0.2 </param>
        <param name="NU_fogColor">1 1 1 0 </param>
        <param name="NU_diffuseColor">1 1 1 1 </param>
        <param name="NU_materialHash">ccabbb4 0 0 0 </param>
      </material>
    </polygon>
    <polygon id="1">
      <material flags="a4010041" srcFactor="0" dstFactor="0" AlphaFunc="0" AlphaTest="0" RefAlpha="0" cullmode="405" zbuffoff="0">
        <texture hash="2000021f" wrapmodeS="2" wrapmodeT="2" minfilter="2" magfilter="2" mipdetail="6" />
        <param name="NU_colorSamplerUV">1 1 0 0 </param>
        <param name="NU_fogParams">40 1200 0 0.2 </param>
        <param name="NU_fogColor">1 1 1 0 </param>
        <param name="NU_diffuseColor">1 1 1 1 </param>
        <param name="NU_materialHash">4771f6e8 0 0 0 </param>
      </material>
    </polygon>
  </mesh>
</NUDMATERIAL>